tipcc/__init__.py
tipcc-0.0.1.dist-info/LICENSE
tipcc-0.0.1.dist-info/METADATA
tipcc-0.0.1.dist-info/WHEEL
tipcc-0.0.1.dist-info/top_level.txt
tipcc-0.0.1.dist-info/RECORD
