Metadata-Version: 2.1
Name: tipcc
Version: 0.0.1
Summary: Tools for interacting with the tip.cc api
Home-page: https://github.com/UpByTheStars/tipcc.py
Author: UpByTheStars
Author-email: upbythestars@gmail.com
Classifier: Programming Language :: Python :: 3
Classifier: License :: OSI Approved :: MIT License
Classifier: Operating System :: OS Independent
Requires-Python: >=3.6
License-File: LICENSE
